hvakr/__init__.py
hvakr/client.py
hvakr/exceptions.py
hvakr/py.typed
hvakr/schemas/__init__.py
hvakr/schemas/common.py
hvakr/schemas/graph.py
hvakr/schemas/outputs.py
hvakr/schemas/project.py
hvakr/schemas/revit.py
hvakr/schemas/weather.py
hvakr-0.1.0.dist-info/METADATA
hvakr-0.1.0.dist-info/WHEEL
hvakr-0.1.0.dist-info/licenses/LICENSE
hvakr-0.1.0.dist-info/RECORD
