Metadata-Version: 2.4
Name: hvakr
Version: 0.1.0
Summary: Official Python SDK for the HVAKR API - HVAC load calculation and building analysis
Project-URL: Homepage, https://hvakr.com
Project-URL: Documentation, https://github.com/flowcircuits/hvakr-python
Project-URL: Repository, https://github.com/flowcircuits/hvakr-python
Project-URL: Issues, https://github.com/flowcircuits/hvakr-python/issues
Author: FLOW CIRCUITS INC
License-Expression: MIT
License-File: LICENSE
Keywords: api-client,building-analysis,hvac,hvakr,load-calculation
Classifier: Development Status :: 4 - Beta
Classifier: Intended Audience :: Developers
Classifier: License :: OSI Approved :: MIT License
Classifier: Operating System :: OS Independent
Classifier: Programming Language :: Python :: 3
Classifier: Programming Language :: Python :: 3.10
Classifier: Programming Language :: Python :: 3.11
Classifier: Programming Language :: Python :: 3.12
Classifier: Programming Language :: Python :: 3.13
Classifier: Typing :: Typed
Requires-Python: >=3.10
Requires-Dist: httpx>=0.25.0
Requires-Dist: pydantic>=2.0.0
Provides-Extra: dev
Requires-Dist: mypy>=1.0.0; extra == 'dev'
Requires-Dist: pytest-asyncio>=0.21.0; extra == 'dev'
Requires-Dist: pytest-httpx>=0.21.0; extra == 'dev'
Requires-Dist: pytest>=7.0.0; extra == 'dev'
Requires-Dist: ruff>=0.1.0; extra == 'dev'
